image_analysis_sd/__init__.py
image_analysis_sd/__main__.py
image_analysis_sd/core.py
image_analysis_sd-0.1.0.dist-info/licenses/LICENSE
image_analysis_sd-0.1.0.dist-info/METADATA
image_analysis_sd-0.1.0.dist-info/WHEEL
image_analysis_sd-0.1.0.dist-info/entry_points.txt
image_analysis_sd-0.1.0.dist-info/top_level.txt
image_analysis_sd-0.1.0.dist-info/RECORD
