Metadata-Version: 2.4
Name: image_analysis_sd
Version: 0.1.0
Summary: Reverse Stable Diffusion utilities and CLI
Author-email: chazz <you@example.com>
License-Expression: MIT
Requires-Python: >=3.13
License-File: LICENSE
Requires-Dist: annotated-types==0.7.0
Requires-Dist: anyio==4.10.0
Requires-Dist: certifi==2025.8.3
Requires-Dist: charset-normalizer==3.4.3
Requires-Dist: exceptiongroup==1.3.0
Requires-Dist: h11==0.16.0
Requires-Dist: httpcore==1.0.9
Requires-Dist: httpx==0.28.1
Requires-Dist: idna==3.10
Requires-Dist: ollama==0.5.3
Requires-Dist: pillow==11.3.0
Requires-Dist: pydantic==2.11.7
Requires-Dist: pydantic-core==2.33.2
Requires-Dist: requests==2.32.5
Requires-Dist: sniffio==1.3.1
Requires-Dist: typing-inspection==0.4.1
Requires-Dist: typing-extensions==4.15.0
Requires-Dist: urllib3==2.5.0
Dynamic: license-file
